{
    "next_cursor": "MTczNjcyNjQwMDAwMCwzODY3MTIxNQ==",
    "total_results": 11480721,
    "per_page": 10,
    "data": [
        {
            "id": "8a8452c9-9587-4a12-a71a-71ff1e0e7216",
            "title": "Chris Hemsworth Centr Trainer Rulk's Bodyweight Workout",
            "source_title": "menshealth.com",
            "source_link": "menshealth.com",
            "article_link": "https://www.menshealth.com/fitness/a33393649/centr-app-rulk-bodyweight-workout/",
            "keywords": [],
            "topics": [],
            "description": "This functional bodyweight workout series from Chris Hemsworth's Centr app trainer Da Rulk requires no equipment.",
            "pub_date": "2096-02-15T00:00:00",
            "creator": "Emily Shiffer",
            "content": "Chris Hemsworth has been one of the most visible celebrities in the fitness space over the last few ...",
            "media_url": "https://hips.hearstapps.com/hmg-prod/images/09-27-19-centr-2096-2-1595447526.jpg?crop=1.00xw:0.752xh;0,0.188xh&resize=1200:*",
            "media_type": "image/jpeg",
            "media_description": null,
            "media_credit": null,
            "media_thumbnail": null,
            "language": "en",
            "sentiment": {}
        },
        {
            "id": "11d85dc7-a98f-43f7-859f-4faa18c25589",
            "title": "Get In Touch With Licensed Real Estate Agents For Selling Your Property",
            "source_title": "express-press-release.net",
            "source_link": "express-press-release.net",
            "article_link": "https://express-press-release.net/news/2021/09/16/1016040",
            "keywords": [],
            "topics": [],
            "description": "Ontario, Canada, 2021-Sep-16 — /EPR Network/ — When deciding which real estate agent to hire can be the most dreaded part of the process. The problem is tha",
            "pub_date": "2031-03-20T00:00:00",
            "creator": "Arslan Ahmad",
            "content": "Ontario, Canada, 2021-Sep-16 — /EPR Network/ — When deciding which real estate agent to hire can be ...",
            "media_url": "https://express-press-release.net/news/2021/09/16/1016040",
            "media_type": "image/jpeg",
            "media_description": null,
            "media_credit": null,
            "media_thumbnail": null,
            "language": "en",
            "sentiment": {}
        },
        {
            "id": "ab7b2e31-3e1e-487b-89de-229ff926edcc",
            "title": "'WandaVision' Star Elizabeth Olsen Reacts to Scarlet Witch Return Rumors",
            "source_title": "menshealth.com",
            "source_link": "menshealth.com",
            "article_link": "https://www.menshealth.com/entertainment/a41463550/elizabeth-olsen-scarlet-witch-return-rumours/",
            "keywords": [],
            "topics": [],
            "description": "WandaVision's Elizabeth Olsen has addressed Scarlet Witch return rumours for the Agatha: Coven of Chaos spinoff series.",
            "pub_date": "2030-01-19T00:00:00",
            "creator": "Sam Warner",
            "content": "Elizabeth Olsen has addressed rumors that she could return as Scarlet Witch again in the upcoming Wa...",
            "media_url": "https://hips.hearstapps.com/hmg-prod/images/wanda-doctor-strange-in-the-multiverse-of-madness-1640190130.jpg?crop=0.813xw:1.00xh;0.0946xw,0&resize=1200:*",
            "media_type": "image/jpeg",
            "media_description": null,
            "media_credit": null,
            "media_thumbnail": null,
            "language": "en",
            "sentiment": {}
        },
        {
            "id": "6a367603-5ebd-488a-bdd0-ecdb1cfba81c",
            "title": "Rising Prices Are Not the Enemy",
            "source_title": "thenewamerican.com",
            "source_link": "thenewamerican.com",
            "article_link": "https://thenewamerican.com/print/rising-prices-are-not-the-enemy/",
            "keywords": [],
            "topics": [],
            "description": "Questioning the causes of inflation and rent controls? Explore The War on Prices for alternative viewpoints and a deeper understanding of the economy.",
            "pub_date": "2025-01-13T00:00:00",
            "creator": null,
            "content": "What we find in these pages runs against the current torrent of mainstream media and conformist poli...",
            "media_url": "https://thenewamerican.com/assets/sites/2/2024/book-1-scaled.jpg",
            "media_type": "image/jpeg",
            "media_description": null,
            "media_credit": null,
            "media_thumbnail": null,
            "language": "en",
            "sentiment": {}
        },
        {
            "id": "97c7e201-222c-41d6-a1d9-0a842faf8783",
            "title": "Rising Prices Are Not the Enemy",
            "source_title": "thenewamerican.com",
            "source_link": "thenewamerican.com",
            "article_link": "https://thenewamerican.com/print/rising-prices-are-not-the-enemy/?add-to-cart=292337",
            "keywords": [],
            "topics": [],
            "description": "Questioning the causes of inflation and rent controls? Explore The War on Prices for alternative viewpoints and a deeper understanding of the economy.",
            "pub_date": "2025-01-13T00:00:00",
            "creator": null,
            "content": "What we find in these pages runs against the current torrent of mainstream media and conformist poli...",
            "media_url": "https://thenewamerican.com/assets/sites/2/2024/book-1-scaled.jpg",
            "media_type": "image/jpeg",
            "media_description": null,
            "media_credit": null,
            "media_thumbnail": null,
            "language": "en",
            "sentiment": {}
        },
        {
            "id": "dc6c04b9-2f07-4228-a958-7fce79c0be62",
            "title": "CIA Democrats Infiltrate Congress",
            "source_title": "thenewamerican.com",
            "source_link": "thenewamerican.com",
            "article_link": "https://thenewamerican.com/print/cia-democrats-infiltrate-congress/?add-to-cart=292338",
            "keywords": [],
            "topics": [],
            "description": "Get the inside scoop on CIA Democrats infiltrating Congress. Learn how their expertise in intelligence and military affairs impact policy.",
            "pub_date": "2025-01-13T00:00:00",
            "creator": null,
            "content": "The headline over the NBC News report in December 2023 seemed innocuous enough: “Democratic lawmaker...",
            "media_url": "https://thenewamerican.com/assets/sites/2/2024/4101-congress1.jpg",
            "media_type": "image/jpeg",
            "media_description": null,
            "media_credit": null,
            "media_thumbnail": null,
            "language": "en",
            "sentiment": {}
        },
        {
            "id": "1a882972-399d-4c52-a0db-8677e94780e0",
            "title": "Popes Against Collectivism",
            "source_title": "thenewamerican.com",
            "source_link": "thenewamerican.com",
            "article_link": "https://thenewamerican.com/print/popes-against-collectivism/?add-to-cart=292337",
            "keywords": [],
            "topics": [],
            "description": "Explore the strong stance of Catholic popes against socialism and communism throughout history. Learn about their condemnations and teachings.",
            "pub_date": "2025-01-13T00:00:00",
            "creator": null,
            "content": "For more than a century and a half before Pope Francis, Catholic popes have condemned the evils of s...",
            "media_url": "https://thenewamerican.com/assets/sites/2/_PRINT/subscribe/digital-image.jpg",
            "media_type": "image/jpeg",
            "media_description": null,
            "media_credit": null,
            "media_thumbnail": null,
            "language": "en",
            "sentiment": {}
        },
        {
            "id": "63ff3ff8-d9c6-434e-8971-72cd8d037502",
            "title": "Secret Agreement That Neutralized the Catholic Church",
            "source_title": "thenewamerican.com",
            "source_link": "thenewamerican.com",
            "article_link": "https://thenewamerican.com/print/secret-agreement-that-neutralized-the-catholic-church/?add-to-cart=292338",
            "keywords": [],
            "topics": [],
            "description": "Explore the historical information essential for understanding the crisis in the Catholic Church. Learn about the secret agreement and its impact.",
            "pub_date": "2025-01-13T00:00:00",
            "creator": null,
            "content": "This article by the late John F. McManus, published by The New American in December 1985, provides i...",
            "media_url": "https://thenewamerican.com/assets/sites/2/2024/4101-secret1.jpg",
            "media_type": "image/jpeg",
            "media_description": null,
            "media_credit": null,
            "media_thumbnail": null,
            "language": "en",
            "sentiment": {}
        },
        {
            "id": "0c26c4ac-5b45-45b8-a709-da55b147c79e",
            "title": "QuickQuotes",
            "source_title": "thenewamerican.com",
            "source_link": "thenewamerican.com",
            "article_link": "https://thenewamerican.com/print/quick-quotes-77/?add-to-cart=292338",
            "keywords": [],
            "topics": [],
            "description": "Find out why California wildfires persist despite mild drought conditions. Explore the importance of forest management practices in preventing wildfires.",
            "pub_date": "2025-01-13T00:00:00",
            "creator": null,
            "content": "“As far as we can tell, California is prone to wildfires regardless of whether conditions are dry......",
            "media_url": "https://thenewamerican.com/assets/sites/2/_PRINT/subscribe/digital-image.jpg",
            "media_type": "image/jpeg",
            "media_description": null,
            "media_credit": null,
            "media_thumbnail": null,
            "language": "en",
            "sentiment": {}
        },
        {
            "id": "6a321c53-b17b-4b03-9d4f-a58db4da54cc",
            "title": "Behind the Founders",
            "source_title": "thenewamerican.com",
            "source_link": "thenewamerican.com",
            "article_link": "https://thenewamerican.com/print/behind-the-founders/",
            "keywords": [],
            "topics": [],
            "description": "Dive into the research and documented evidence behind the creation of the federal republic by the Founding Fathers.",
            "pub_date": "2025-01-13T00:00:00",
            "creator": null,
            "content": "In his keynote address at the 1916 Republican National Convention, and then again in his 1921 inaugu...",
            "media_url": "https://thenewamerican.com/assets/sites/2/2024/4101-review1.jpg",
            "media_type": "image/jpeg",
            "media_description": null,
            "media_credit": null,
            "media_thumbnail": null,
            "language": "en",
            "sentiment": {}
        }
    ]
}